tests/__init__.py
tests/test_calculation.py
tests/test_download.py
tests/test_info.py
tests/test_ingest.py
tests/test_utils.py
wrfup/__init__.py
wrfup/calculation.py
wrfup/download.py
wrfup/info.py
wrfup/ingest.py
wrfup/main.py
wrfup/utils.py
wrfup-1.0.8.dist-info/LICENSE
wrfup-1.0.8.dist-info/METADATA
wrfup-1.0.8.dist-info/WHEEL
wrfup-1.0.8.dist-info/entry_points.txt
wrfup-1.0.8.dist-info/top_level.txt
wrfup-1.0.8.dist-info/RECORD
