Metadata-Version: 2.1
Name: wrfup
Version: 1.0.8
Summary: A Python package to ingest global urban data into WRF geo_em files.
Home-page: https://github.com/jacobogabeiraspenas/wrfup
Author: Jacobo Gabeiras Penas
Author-email: Jacobo Gabeiras Penas <jacobogabeiras@gmail.com>
License: MIT
Requires-Python: >=3.8
License-File: LICENSE
Requires-Dist: numpy<2.0,>=1.24
Requires-Dist: tqdm<5.0,>=4.62
Requires-Dist: requests<3.0,>=2.32
Requires-Dist: netCDF4<2.0,>=1.7
Requires-Dist: pandas<3.0,>=2.2
Requires-Dist: shapely<3.0,>=2.0
Requires-Dist: fiona<2.0,>=1.10
Requires-Dist: rasterio<2.0,>=1.4
Requires-Dist: xarray<2025.0,>=2024.7
Requires-Dist: scipy<2.0,>=1.13
